Metadata-Version: 2.1
Name: milwaukee-dpw-parser
Version: 0.1.0
Summary: Milwaukee Wisconsin Department of Public Works Parser
Home-page: https://github.com/jasonfry89/milwaukee-dpw-parser
Author: Jason Fry
License: MIT
Keywords: Milwaukee,Wisconsin,Garbage,Recycling,DPW
Platform: UNKNOWN
Requires-Python: >=3
